sqlcycli-2.0.3.dist-info/WHEEL
sqlcycli-2.0.3.dist-info/top_level.txt
sqlcycli-2.0.3.dist-info/METADATA
sqlcycli-2.0.3.dist-info/RECORD
sqlcycli-2.0.3.dist-info/licenses/LICENSE
sqlcycli/sqlintvl.pyi
sqlcycli/utils.pyi
sqlcycli/transcode.c
sqlcycli/utils.cpython-311-x86_64-linux-gnu.so
sqlcycli/charset.cpython-311-x86_64-linux-gnu.so
sqlcycli/protocol.pxd
sqlcycli/transcode.pxd
sqlcycli/_optionfile.c
sqlcycli/_connect.py
sqlcycli/sqlfunc.pxd
sqlcycli/sqlfunc.c
sqlcycli/connection.pxd
sqlcycli/connection.c
sqlcycli/sqlintvl.pxd
sqlcycli/charset.py
sqlcycli/sqlfunc.py
sqlcycli/_ssl.cpython-311-x86_64-linux-gnu.so
sqlcycli/_auth.pyi
sqlcycli/errors.c
sqlcycli/_auth.c
sqlcycli/charset.pyi
sqlcycli/protocol.cpython-311-x86_64-linux-gnu.so
sqlcycli/utils.pyx
sqlcycli/_optionfile.pxd
sqlcycli/_optionfile.pyi
sqlcycli/protocol.c
sqlcycli/charset.c
sqlcycli/_auth.py
sqlcycli/_connect.pxd
sqlcycli/_ssl.pyi
sqlcycli/sqlintvl.cpython-311-x86_64-linux-gnu.so
sqlcycli/connection.cpython-311-x86_64-linux-gnu.so
sqlcycli/_ssl.c
sqlcycli/utils.pxd
sqlcycli/connection.pyi
sqlcycli/_auth.pxd
sqlcycli/_connect.c
sqlcycli/sqlintvl.c
sqlcycli/transcode.pyi
sqlcycli/sqlintvl.py
sqlcycli/transcode.pyx
sqlcycli/_optionfile.cpython-311-x86_64-linux-gnu.so
sqlcycli/_ssl.pxd
sqlcycli/transcode.cpython-311-x86_64-linux-gnu.so
sqlcycli/errors.cpython-311-x86_64-linux-gnu.so
sqlcycli/utils.c
sqlcycli/charset.pxd
sqlcycli/_ssl.py
sqlcycli/_auth.cpython-311-x86_64-linux-gnu.so
sqlcycli/errors.pxd
sqlcycli/sqlfunc.pyi
sqlcycli/__init__.pxd
sqlcycli/__init__.py
sqlcycli/_connect.cpython-311-x86_64-linux-gnu.so
sqlcycli/sqlfunc.cpython-311-x86_64-linux-gnu.so
sqlcycli/errors.py
sqlcycli/protocol.py
sqlcycli/_optionfile.py
sqlcycli/connection.py
sqlcycli/aio/connection.pxd
sqlcycli/aio/connection.c
sqlcycli/aio/pool.c
sqlcycli/aio/pool.pyi
sqlcycli/aio/pool.cpython-311-x86_64-linux-gnu.so
sqlcycli/aio/connection.cpython-311-x86_64-linux-gnu.so
sqlcycli/aio/pool.py
sqlcycli/aio/connection.pyi
sqlcycli/aio/pool.pxd
sqlcycli/aio/__init__.pxd
sqlcycli/aio/__init__.py
sqlcycli/aio/connection.py
