Metadata-Version: 2.4
Name: sqlcycli
Version: 2.0.3
Summary: Fast MySQL driver build in Cython (Sync and Async).
Home-page: https://github.com/AresJef/SQLCyCli
Author: Jiefu Chen
Author-email: keppa1991@163.com
License: MIT license
Keywords: mysql,mariadb,pymysql,aiomysql,cython,asyncio
Classifier: Programming Language :: Python :: 3
Classifier: Operating System :: Unix
Classifier: Operating System :: MacOS :: MacOS X
Classifier: Operating System :: Microsoft :: Windows
Requires-Python: >=3.10
License-File: LICENSE
Requires-Dist: cytimes>=3.0.1
Requires-Dist: numpy>=1.25.2
Requires-Dist: orjson>=3.10.2
Requires-Dist: pandas>=2.1.0
Requires-Dist: typing-extensions>=4.9.0
Dynamic: license-file
